promplate_recipes-0.2.3.3.dist-info/METADATA
promplate_recipes-0.2.3.3.dist-info/WHEEL
promplate_recipes-0.2.3.3.dist-info/entry_points.txt
promplate_recipes/__init__.py
promplate_recipes/context.py
promplate_recipes/functional/_common.py
promplate_recipes/functional/component.py
promplate_recipes/functional/node.py
promplate_recipes/version.py
promplate_recipes-0.2.3.3.dist-info/RECORD
