Metadata-Version: 2.1
Name: promplate-recipes
Version: 0.2.3.3
Author-Email: Muspi Merol <me@promplate.dev>
License: MIT
Requires-Python: >=3.10
Requires-Dist: promplate<0.4,>=0.3.5.1
Requires-Dist: python-box~=7.1
